smartalloc/__init__.py
smartalloc-0.0.1.dist-info/METADATA
smartalloc-0.0.1.dist-info/RECORD
smartalloc-0.0.1.dist-info/WHEEL
smartalloc-0.0.1.dist-info/top_level.txt
